Metadata-Version: 2.1
Name: pulumi-kubernetes-proxy
Version: 0.1.2
Summary: A Pulumi package for managing Kubernetes proxies during provisioning.
Home-page: UNKNOWN
License: Apache-2.0
Project-URL: Repository, https://github.com/benesch/pulumi-kubernetes-proxy
Platform: UNKNOWN
